setup.py
distributions_usuieri/Binomialdistribution.py
distributions_usuieri/Gaussiandistribution.py
distributions_usuieri/Generaldistribution.py
distributions_usuieri/__init__.py
distributions_usuieri.egg-info/PKG-INFO
distributions_usuieri.egg-info/SOURCES.txt
distributions_usuieri.egg-info/dependency_links.txt
distributions_usuieri.egg-info/not-zip-safe
distributions_usuieri.egg-info/top_level.txt