Metadata-Version: 1.0
Name: distributions-usuieri
Version: 0.1
Summary: Gaussian distributions
Home-page: UNKNOWN
Author: Erica Usui
Author-email: UNKNOWN
License: UNKNOWN
Platform: UNKNOWN
